{
  "scrapedAt": "2025-08-09T16:25:20.602Z",
  "vividSeats": [
    {
      "title": "Oasis with Cage The Elephant",
      "date": "Thu Aug 28•7:30 PM",
      "venue": "Soldier Field",
      "url": "https://www.vividseats.com/oasis-tickets-chicago-soldier-field-8-28-2025--concerts-alternative/production/5262360",
      "listings": [
        {
          "section": "N/A",
          "row": "33",
          "price": 590,
          "ticketCount": 2,
          "feesIncluded": true
        },
        {
          "section": "N/A",
          "row": "15",
          "price": 601,
          "ticketCount": 4,
          "feesIncluded": true
        },
        {
          "section": "N/A",
          "row": "12",
          "price": 615,
          "ticketCount": 2,
          "feesIncluded": true
        },
        {
          "section": "N/A",
          "row": "31",
          "price": 618,
          "ticketCount": 2,
          "feesIncluded": true
        },
        {
          "section": "N/A",
          "row": "34",
          "price": 619,
          "ticketCount": 2,
          "feesIncluded": true
        },
        {
          "section": "N/A",
          "row": "17",
          "price": 628,
          "ticketCount": 2,
          "feesIncluded": true
        },
        {
          "section": "N/A",
          "row": "26",
          "price": 630,
          "ticketCount": 2,
          "feesIncluded": true
        },
        {
          "section": "N/A",
          "row": "32",
          "price": 630,
          "ticketCount": 4,
          "feesIncluded": true
        },
        {
          "section": "N/A",
          "row": "16",
          "price": 635,
          "ticketCount": 2,
          "feesIncluded": true
        },
        {
          "section": "N/A",
          "row": "12",
          "price": 636,
          "ticketCount": 4,
          "feesIncluded": true
        },
        {
          "section": "N/A",
          "row": "20",
          "price": 647,
          "ticketCount": 2,
          "feesIncluded": true
        },
        {
          "section": "N/A",
          "row": "14",
          "price": 656,
          "ticketCount": 2,
          "feesIncluded": true
        },
        {
          "section": "N/A",
          "row": "11",
          "price": 658,
          "ticketCount": 4,
          "feesIncluded": true
        },
        {
          "section": "N/A",
          "row": "32",
          "price": 658,
          "ticketCount": 2,
          "feesIncluded": true
        },
        {
          "section": "N/A",
          "row": "10",
          "price": 660,
          "ticketCount": 2,
          "feesIncluded": true
        },
        {
          "section": "N/A",
          "row": "25",
          "price": 662,
          "ticketCount": 2,
          "feesIncluded": true
        },
        {
          "section": "N/A",
          "row": "20",
          "price": 674,
          "ticketCount": 2,
          "feesIncluded": true
        },
        {
          "section": "N/A",
          "row": "21",
          "price": 674,
          "ticketCount": 1,
          "feesIncluded": true
        },
        {
          "section": "N/A",
          "row": "21",
          "price": 677,
          "ticketCount": 4,
          "feesIncluded": true
        },
        {
          "section": "N/A",
          "row": "10",
          "price": 679,
          "ticketCount": 4,
          "feesIncluded": true
        }
      ],
      "minPrice": 590,
      "maxPrice": 679
    },
    {
      "title": "Chris Brown",
      "date": "Thu Aug 28•7:00 PM",
      "venue": "Wrigley Field",
      "url": "https://www.vividseats.com/chris-brown-tickets-chicago-wrigley-field-8-28-2025--concerts-rb/production/5660623",
      "listings": [
        {
          "section": "N/A",
          "row": "9",
          "price": 311,
          "ticketCount": 2,
          "feesIncluded": true
        },
        {
          "section": "N/A",
          "row": "9",
          "price": 312,
          "ticketCount": 2,
          "feesIncluded": true
        },
        {
          "section": "N/A",
          "row": "9",
          "price": 312,
          "ticketCount": 2,
          "feesIncluded": true
        },
        {
          "section": "N/A",
          "row": "9",
          "price": 313,
          "ticketCount": 2,
          "feesIncluded": true
        },
        {
          "section": "N/A",
          "row": "9",
          "price": 314,
          "ticketCount": 6,
          "feesIncluded": true
        },
        {
          "section": "N/A",
          "row": "9",
          "price": 315,
          "ticketCount": 2,
          "feesIncluded": true
        },
        {
          "section": "N/A",
          "row": "9",
          "price": 316,
          "ticketCount": 5,
          "feesIncluded": true
        },
        {
          "section": "N/A",
          "row": "9",
          "price": 316,
          "ticketCount": 8,
          "feesIncluded": true
        },
        {
          "section": "N/A",
          "row": "7",
          "price": 317,
          "ticketCount": 2,
          "feesIncluded": true
        },
        {
          "section": "N/A",
          "row": "8",
          "price": 317,
          "ticketCount": 4,
          "feesIncluded": true
        },
        {
          "section": "N/A",
          "row": "8",
          "price": 317,
          "ticketCount": 6,
          "feesIncluded": true
        },
        {
          "section": "N/A",
          "row": "8",
          "price": 318,
          "ticketCount": 2,
          "feesIncluded": true
        },
        {
          "section": "N/A",
          "row": "8",
          "price": 319,
          "ticketCount": 7,
          "feesIncluded": true
        },
        {
          "section": "N/A",
          "row": "7",
          "price": 319,
          "ticketCount": 2,
          "feesIncluded": true
        },
        {
          "section": "N/A",
          "row": "8",
          "price": 320,
          "ticketCount": 2,
          "feesIncluded": true
        },
        {
          "section": "N/A",
          "row": "5",
          "price": 320,
          "ticketCount": 4,
          "feesIncluded": true
        },
        {
          "section": "N/A",
          "row": "8",
          "price": 320,
          "ticketCount": 2,
          "feesIncluded": true
        },
        {
          "section": "N/A",
          "row": "7",
          "price": 320,
          "ticketCount": 4,
          "feesIncluded": true
        },
        {
          "section": "N/A",
          "row": "7",
          "price": 321,
          "ticketCount": 5,
          "feesIncluded": true
        },
        {
          "section": "N/A",
          "row": "4",
          "price": 321,
          "ticketCount": 2,
          "feesIncluded": true
        }
      ],
      "minPrice": 311,
      "maxPrice": 321
    },
    {
      "title": "System of A Down and Avenged Sevenfold with Polyphia",
      "date": "Sun Aug 31•5:30 PM+1 Date",
      "venue": "Soldier Field",
      "url": "https://www.vividseats.com/system-of-a-down-tickets-chicago-soldier-field-parking-8-31-2025--concerts-hard-rock/production/5410871",
      "listings": [
        {
          "section": "N/A",
          "row": "27",
          "price": 181,
          "ticketCount": 4,
          "feesIncluded": true
        },
        {
          "section": "N/A",
          "row": "27",
          "price": 184,
          "ticketCount": 2,
          "feesIncluded": true
        },
        {
          "section": "N/A",
          "row": "23",
          "price": 185,
          "ticketCount": 2,
          "feesIncluded": true
        },
        {
          "section": "N/A",
          "row": "20",
          "price": 187,
          "ticketCount": 2,
          "feesIncluded": true
        },
        {
          "section": "N/A",
          "row": "13",
          "price": 193,
          "ticketCount": 2,
          "feesIncluded": true
        },
        {
          "section": "N/A",
          "row": "18",
          "price": 195,
          "ticketCount": 3,
          "feesIncluded": true
        },
        {
          "section": "N/A",
          "row": "5",
          "price": 195,
          "ticketCount": 4,
          "feesIncluded": true
        },
        {
          "section": "N/A",
          "row": "12",
          "price": 195,
          "ticketCount": 2,
          "feesIncluded": true
        },
        {
          "section": "N/A",
          "row": "32",
          "price": 198,
          "ticketCount": 2,
          "feesIncluded": true
        },
        {
          "section": "N/A",
          "row": "26",
          "price": 198,
          "ticketCount": 1,
          "feesIncluded": true
        },
        {
          "section": "N/A",
          "row": "14",
          "price": 199,
          "ticketCount": 2,
          "feesIncluded": true
        },
        {
          "section": "N/A",
          "row": "2",
          "price": 200,
          "ticketCount": 2,
          "feesIncluded": true
        },
        {
          "section": "N/A",
          "row": "8",
          "price": 200,
          "ticketCount": 4,
          "feesIncluded": true
        },
        {
          "section": "N/A",
          "row": "27",
          "price": 201,
          "ticketCount": 2,
          "feesIncluded": true
        },
        {
          "section": "N/A",
          "row": "13",
          "price": 201,
          "ticketCount": 2,
          "feesIncluded": true
        },
        {
          "section": "N/A",
          "row": "28",
          "price": 202,
          "ticketCount": 4,
          "feesIncluded": true
        },
        {
          "section": "N/A",
          "row": "13",
          "price": 202,
          "ticketCount": 4,
          "feesIncluded": true
        },
        {
          "section": "N/A",
          "row": "11",
          "price": 202,
          "ticketCount": 2,
          "feesIncluded": true
        },
        {
          "section": "N/A",
          "row": "15",
          "price": 203,
          "ticketCount": 4,
          "feesIncluded": true
        },
        {
          "section": "N/A",
          "row": "26",
          "price": 203,
          "ticketCount": 2,
          "feesIncluded": true
        }
      ],
      "minPrice": 181,
      "maxPrice": 203
    }
  ],
  "stubHub": [],
  "opportunities": [
    {
      "event": "Oasis with Cage The Elephant",
      "date": "Thu Aug 28•7:30 PM",
      "venue": "Soldier Field",
      "buyFrom": "VividSeats",
      "buyPrice": 590,
      "sellOn": "StubHub",
      "sellPrice": "708.00",
      "minTicketCount": 1,
      "profitPerTicket": "118.00",
      "profitMargin": "20% (estimated)",
      "lastUpdated": "2025-08-09T16:25:20.602Z"
    },
    {
      "event": "Chris Brown",
      "date": "Thu Aug 28•7:00 PM",
      "venue": "Wrigley Field",
      "buyFrom": "VividSeats",
      "buyPrice": 311,
      "sellOn": "StubHub",
      "sellPrice": "373.20",
      "minTicketCount": 2,
      "profitPerTicket": "62.20",
      "profitMargin": "20% (estimated)",
      "lastUpdated": "2025-08-09T16:25:20.602Z"
    },
    {
      "event": "System of A Down and Avenged Sevenfold with Polyphia",
      "date": "Sun Aug 31•5:30 PM+1 Date",
      "venue": "Soldier Field",
      "buyFrom": "VividSeats",
      "buyPrice": 181,
      "sellOn": "StubHub",
      "sellPrice": "217.20",
      "minTicketCount": 1,
      "profitPerTicket": "36.20",
      "profitMargin": "20% (estimated)",
      "lastUpdated": "2025-08-09T16:25:20.602Z"
    }
  ]
}