{
  "scrapedAt": "2025-10-14T08:25:08.589Z",
  "vividSeats": [
    {
      "title": "Billie Eilish",
      "date": "Sat Nov 22•7:00 PM+1 Date",
      "venue": "Chase Center",
      "url": "https://www.vividseats.com/billie-eilish-tickets-san-francisco-chase-center-11-22-2025--concerts-pop/production/5768485",
      "listings": [
        {
          "section": "N/A",
          "row": "18",
          "price": 225,
          "ticketCount": 2,
          "feesIncluded": true
        },
        {
          "section": "N/A",
          "row": "20",
          "price": 231,
          "ticketCount": 2,
          "feesIncluded": true
        },
        {
          "section": "N/A",
          "row": "14",
          "price": 233,
          "ticketCount": 4,
          "feesIncluded": true
        },
        {
          "section": "N/A",
          "row": "12",
          "price": 233,
          "ticketCount": 3,
          "feesIncluded": true
        },
        {
          "section": "N/A",
          "row": "17",
          "price": 236,
          "ticketCount": 2,
          "feesIncluded": true
        },
        {
          "section": "N/A",
          "row": "19",
          "price": 240,
          "ticketCount": 2,
          "feesIncluded": true
        },
        {
          "section": "N/A",
          "row": "19",
          "price": 240,
          "ticketCount": 2,
          "feesIncluded": true
        },
        {
          "section": "N/A",
          "row": "17",
          "price": 241,
          "ticketCount": 2,
          "feesIncluded": true
        },
        {
          "section": "N/A",
          "row": "15",
          "price": 242,
          "ticketCount": 2,
          "feesIncluded": true
        },
        {
          "section": "N/A",
          "row": "15",
          "price": 242,
          "ticketCount": 4,
          "feesIncluded": true
        },
        {
          "section": "N/A",
          "row": "13",
          "price": 244,
          "ticketCount": 4,
          "feesIncluded": true
        },
        {
          "section": "N/A",
          "row": "5",
          "price": 244,
          "ticketCount": 2,
          "feesIncluded": true
        },
        {
          "section": "N/A",
          "row": "12",
          "price": 248,
          "ticketCount": 2,
          "feesIncluded": true
        },
        {
          "section": "N/A",
          "row": "9",
          "price": 248,
          "ticketCount": 2,
          "feesIncluded": true
        },
        {
          "section": "N/A",
          "row": "19",
          "price": 248,
          "ticketCount": 2,
          "feesIncluded": true
        },
        {
          "section": "N/A",
          "row": "6",
          "price": 248,
          "ticketCount": 2,
          "feesIncluded": true
        },
        {
          "section": "N/A",
          "row": "21",
          "price": 249,
          "ticketCount": 2,
          "feesIncluded": true
        },
        {
          "section": "N/A",
          "row": "11",
          "price": 249,
          "ticketCount": 2,
          "feesIncluded": true
        },
        {
          "section": "N/A",
          "row": "18",
          "price": 250,
          "ticketCount": 2,
          "feesIncluded": true
        },
        {
          "section": "N/A",
          "row": "6",
          "price": 251,
          "ticketCount": 2,
          "feesIncluded": true
        }
      ],
      "minPrice": 225,
      "maxPrice": 251
    },
    {
      "title": "Ariana Grande",
      "date": "Sat Jun 6•7:30 PM+2 Dates",
      "venue": "Oakland Arena",
      "url": "https://www.vividseats.com/ariana-grande-tickets-oakland-oakland-arena-6-6-2026--concerts-pop/production/5973642",
      "listings": [
        {
          "section": "N/A",
          "row": "19",
          "price": 605,
          "ticketCount": 2,
          "feesIncluded": true
        },
        {
          "section": "N/A",
          "row": "16",
          "price": 611,
          "ticketCount": 2,
          "feesIncluded": true
        },
        {
          "section": "N/A",
          "row": "13",
          "price": 618,
          "ticketCount": 2,
          "feesIncluded": true
        },
        {
          "section": "N/A",
          "row": "12",
          "price": 622,
          "ticketCount": 2,
          "feesIncluded": true
        },
        {
          "section": "N/A",
          "row": "14",
          "price": 623,
          "ticketCount": 2,
          "feesIncluded": true
        },
        {
          "section": "N/A",
          "row": "5",
          "price": 633,
          "ticketCount": 3,
          "feesIncluded": true
        },
        {
          "section": "N/A",
          "row": "17",
          "price": 684,
          "ticketCount": 2,
          "feesIncluded": true
        },
        {
          "section": "N/A",
          "row": "14",
          "price": 732,
          "ticketCount": 1,
          "feesIncluded": true
        },
        {
          "section": "N/A",
          "row": "25",
          "price": 744,
          "ticketCount": 3,
          "feesIncluded": true
        },
        {
          "section": "N/A",
          "row": "12",
          "price": 752,
          "ticketCount": 4,
          "feesIncluded": true
        },
        {
          "section": "N/A",
          "row": "15",
          "price": 777,
          "ticketCount": 2,
          "feesIncluded": true
        },
        {
          "section": "N/A",
          "row": "12",
          "price": 804,
          "ticketCount": 5,
          "feesIncluded": true
        },
        {
          "section": "N/A",
          "row": "18",
          "price": 837,
          "ticketCount": 2,
          "feesIncluded": true
        },
        {
          "section": "N/A",
          "row": "1",
          "price": 845,
          "ticketCount": 3,
          "feesIncluded": true
        },
        {
          "section": "N/A",
          "row": "7",
          "price": 886,
          "ticketCount": 2,
          "feesIncluded": true
        },
        {
          "section": "N/A",
          "row": "2",
          "price": 891,
          "ticketCount": 2,
          "feesIncluded": true
        },
        {
          "section": "N/A",
          "row": "11",
          "price": 913,
          "ticketCount": 3,
          "feesIncluded": true
        },
        {
          "section": "N/A",
          "row": "DS",
          "price": 916,
          "ticketCount": 2,
          "feesIncluded": true
        },
        {
          "section": "N/A",
          "row": "13",
          "price": 929,
          "ticketCount": 3,
          "feesIncluded": true
        },
        {
          "section": "N/A",
          "row": "18",
          "price": 952,
          "ticketCount": 3,
          "feesIncluded": true
        }
      ],
      "minPrice": 605,
      "maxPrice": 952
    },
    {
      "title": "Lorde",
      "date": "Sun Oct 19•6:00 PM",
      "venue": "Greek Theatre - Berkeley",
      "url": "https://www.vividseats.com/lorde-tickets-berkeley-greek-theatre---berkeley-10-19-2025--concerts-pop/production/5744332",
      "listings": [
        {
          "section": "N/A",
          "row": "GA",
          "price": 303,
          "ticketCount": 2,
          "feesIncluded": true
        },
        {
          "section": "N/A",
          "row": "GA",
          "price": 306,
          "ticketCount": 3,
          "feesIncluded": true
        },
        {
          "section": "N/A",
          "row": "GA",
          "price": 326,
          "ticketCount": 6,
          "feesIncluded": true
        },
        {
          "section": "N/A",
          "row": "GA",
          "price": 333,
          "ticketCount": 1,
          "feesIncluded": true
        },
        {
          "section": "N/A",
          "row": "GA",
          "price": 334,
          "ticketCount": 8,
          "feesIncluded": true
        },
        {
          "section": "N/A",
          "row": "GENER..",
          "price": 339,
          "ticketCount": 2,
          "feesIncluded": true
        },
        {
          "section": "N/A",
          "row": "1",
          "price": 586,
          "ticketCount": 8,
          "feesIncluded": true
        },
        {
          "section": "N/A",
          "row": "A",
          "price": 592,
          "ticketCount": 7,
          "feesIncluded": true
        },
        {
          "section": "N/A",
          "row": "2",
          "price": 882,
          "ticketCount": 2,
          "feesIncluded": true
        }
      ],
      "minPrice": 303,
      "maxPrice": 882
    }
  ],
  "stubHub": [],
  "opportunities": [
    {
      "event": "Billie Eilish",
      "date": "Sat Nov 22•7:00 PM+1 Date",
      "venue": "Chase Center",
      "buyFrom": "VividSeats",
      "buyPrice": 225,
      "sellOn": "StubHub",
      "sellPrice": "270.00",
      "minTicketCount": 2,
      "profitPerTicket": "45.00",
      "profitMargin": "20% (estimated)",
      "lastUpdated": "2025-10-14T08:25:08.589Z"
    },
    {
      "event": "Ariana Grande",
      "date": "Sat Jun 6•7:30 PM+2 Dates",
      "venue": "Oakland Arena",
      "buyFrom": "VividSeats",
      "buyPrice": 605,
      "sellOn": "StubHub",
      "sellPrice": "726.00",
      "minTicketCount": 1,
      "profitPerTicket": "121.00",
      "profitMargin": "20% (estimated)",
      "lastUpdated": "2025-10-14T08:25:08.589Z"
    },
    {
      "event": "Lorde",
      "date": "Sun Oct 19•6:00 PM",
      "venue": "Greek Theatre - Berkeley",
      "buyFrom": "VividSeats",
      "buyPrice": 303,
      "sellOn": "StubHub",
      "sellPrice": "363.60",
      "minTicketCount": 1,
      "profitPerTicket": "60.60",
      "profitMargin": "20% (estimated)",
      "lastUpdated": "2025-10-14T08:25:08.589Z"
    }
  ]
}